boto_endpoint_url_shim.py
boto_endpoint_url_shim-0.0.5.dist-info/LICENSE
boto_endpoint_url_shim-0.0.5.dist-info/METADATA
boto_endpoint_url_shim-0.0.5.dist-info/WHEEL
boto_endpoint_url_shim-0.0.5.dist-info/top_level.txt
boto_endpoint_url_shim-0.0.5.dist-info/RECORD
