Metadata-Version: 2.1
Name: boto_endpoint_url_shim
Version: 0.0.5
Summary: A SHIM to allow boto3 and botocore endpoint URL control from env var and config file.
Author-email: Louis Cochen <louis.cochen@protonmail.ch>
Maintainer-email: Louis Cochen <louis.cochen@protonmail.ch>
License: 
Project-URL: Homepage, https://gitlab.com/ljmc/boto-endpoint-url-shim
Project-URL: Bug Tracker, https://gitlab.com/ljmc/boto-endpoint-url-shim/-/issues
Classifier: Development Status :: 3 - Alpha
Classifier: Intended Audience :: Developers
Classifier: Intended Audience :: System Administrators
Classifier: License :: OSI Approved :: Apache Software License
Classifier: Natural Language :: English
Classifier: Operating System :: OS Independent
Classifier: Programming Language :: Python
Classifier: Programming Language :: Python :: 3
Classifier: Programming Language :: Python :: 3.7
Classifier: Programming Language :: Python :: 3.8
Classifier: Programming Language :: Python :: 3.9
Classifier: Programming Language :: Python :: 3.10
Classifier: Programming Language :: Python :: 3.11
Requires-Python: >=3.7
License-File: LICENSE
